[
  {
    "model": "contenttypes.contenttype",
    "pk": 1,
    "fields": {
      "app_label": "admin",
      "model": "logentry"
    }
  },
  {
    "model": "contenttypes.contenttype",
    "pk": 2,
    "fields": {
      "app_label": "auth",
      "model": "permission"
    }
  },
  {
    "model": "contenttypes.contenttype",
    "pk": 3,
    "fields": {
      "app_label": "auth",
      "model": "group"
    }
  },
  {
    "model": "contenttypes.contenttype",
    "pk": 4,
    "fields": {
      "app_label": "contenttypes",
      "model": "contenttype"
    }
  },
  {
    "model": "contenttypes.contenttype",
    "pk": 5,
    "fields": {
      "app_label": "sessions",
      "model": "session"
    }
  },
  {
    "model": "contenttypes.contenttype",
    "pk": 6,
    "fields": {
      "app_label": "event",
      "model": "event"
    }
  },
  {
    "model": "contenttypes.contenttype",
    "pk": 7,
    "fields": {
      "app_label": "event",
      "model": "eventlocation"
    }
  },
  {
    "model": "contenttypes.contenttype",
    "pk": 8,
    "fields": {
      "app_label": "event",
      "model": "eventsponser"
    }
  },
  {
    "model": "contenttypes.contenttype",
    "pk": 9,
    "fields": {
      "app_label": "organisation",
      "model": "organisation"
    }
  },
  {
    "model": "contenttypes.contenttype",
    "pk": 10,
    "fields": {
      "app_label": "user",
      "model": "user"
    }
  },
  {
    "model": "event.eventlocation",
    "pk": 1,
    "fields": {
      "name": "Karachi",
      "address": "DHA",
      "logo": ""
    }
  },
  {
    "model": "event.eventlocation",
    "pk": 2,
    "fields": {
      "name": "Lahore",
      "address": "Gulberg",
      "logo": ""
    }
  },
  {
    "model": "event.eventlocation",
    "pk": 3,
    "fields": {
      "name": "Islamabad",
      "address": "Downtown Islamabad",
      "logo": ""
    }
  },
  {
    "model": "event.eventlocation",
    "pk": 4,
    "fields": {
      "name": "Islamabad",
      "address": "Downtown Islamabad",
      "logo": "location/action-adrenaline-adventure-1047051.jpg"
    }
  },
  {
    "model": "event.eventsponser",
    "pk": 1,
    "fields": {
      "name": "10 pearls",
      "logo": "sponser/action-adrenaline-adventure-1047051.jpg"
    }
  },
  {
    "model": "event.eventsponser",
    "pk": 2,
    "fields": {
      "name": "Folio3",
      "logo": "sponser/action-adrenaline-adventure-1047051_rIFWub2.jpg"
    }
  },
  {
    "model": "event.eventsponser",
    "pk": 3,
    "fields": {
      "name": "TPS",
      "logo": "sponser/action-adrenaline-adventure-1047051_VboTIrT.jpg"
    }
  },
  {
    "model": "event.event",
    "pk": 1,
    "fields": {
      "title": "JS Training",
      "description": "practical example",
      "registration_url": null,
      "start_datetime": "2081-02-08T20:39:00Z",
      "end_datetime": "3938-02-08T15:08:00Z",
      "organisation": 1,
      "location": 1,
      "cover": "",
      "sponser": [
        1,
        3
      ]
    }
  },
  {
    "model": "auth.permission",
    "pk": 1,
    "fields": {
      "name": "Can add log entry",
      "content_type": 1,
      "codename": "add_logentry"
    }
  },
  {
    "model": "auth.permission",
    "pk": 2,
    "fields": {
      "name": "Can change log entry",
      "content_type": 1,
      "codename": "change_logentry"
    }
  },
  {
    "model": "auth.permission",
    "pk": 3,
    "fields": {
      "name": "Can delete log entry",
      "content_type": 1,
      "codename": "delete_logentry"
    }
  },
  {
    "model": "auth.permission",
    "pk": 4,
    "fields": {
      "name": "Can add permission",
      "content_type": 2,
      "codename": "add_permission"
    }
  },
  {
    "model": "auth.permission",
    "pk": 5,
    "fields": {
      "name": "Can change permission",
      "content_type": 2,
      "codename": "change_permission"
    }
  },
  {
    "model": "auth.permission",
    "pk": 6,
    "fields": {
      "name": "Can delete permission",
      "content_type": 2,
      "codename": "delete_permission"
    }
  },
  {
    "model": "auth.permission",
    "pk": 7,
    "fields": {
      "name": "Can add group",
      "content_type": 3,
      "codename": "add_group"
    }
  },
  {
    "model": "auth.permission",
    "pk": 8,
    "fields": {
      "name": "Can change group",
      "content_type": 3,
      "codename": "change_group"
    }
  },
  {
    "model": "auth.permission",
    "pk": 9,
    "fields": {
      "name": "Can delete group",
      "content_type": 3,
      "codename": "delete_group"
    }
  },
  {
    "model": "auth.permission",
    "pk": 10,
    "fields": {
      "name": "Can add content type",
      "content_type": 4,
      "codename": "add_contenttype"
    }
  },
  {
    "model": "auth.permission",
    "pk": 11,
    "fields": {
      "name": "Can change content type",
      "content_type": 4,
      "codename": "change_contenttype"
    }
  },
  {
    "model": "auth.permission",
    "pk": 12,
    "fields": {
      "name": "Can delete content type",
      "content_type": 4,
      "codename": "delete_contenttype"
    }
  },
  {
    "model": "auth.permission",
    "pk": 13,
    "fields": {
      "name": "Can add session",
      "content_type": 5,
      "codename": "add_session"
    }
  },
  {
    "model": "auth.permission",
    "pk": 14,
    "fields": {
      "name": "Can change session",
      "content_type": 5,
      "codename": "change_session"
    }
  },
  {
    "model": "auth.permission",
    "pk": 15,
    "fields": {
      "name": "Can delete session",
      "content_type": 5,
      "codename": "delete_session"
    }
  },
  {
    "model": "auth.permission",
    "pk": 16,
    "fields": {
      "name": "Can add event",
      "content_type": 6,
      "codename": "add_event"
    }
  },
  {
    "model": "auth.permission",
    "pk": 17,
    "fields": {
      "name": "Can change event",
      "content_type": 6,
      "codename": "change_event"
    }
  },
  {
    "model": "auth.permission",
    "pk": 18,
    "fields": {
      "name": "Can delete event",
      "content_type": 6,
      "codename": "delete_event"
    }
  },
  {
    "model": "auth.permission",
    "pk": 19,
    "fields": {
      "name": "Can add event location",
      "content_type": 7,
      "codename": "add_eventlocation"
    }
  },
  {
    "model": "auth.permission",
    "pk": 20,
    "fields": {
      "name": "Can change event location",
      "content_type": 7,
      "codename": "change_eventlocation"
    }
  },
  {
    "model": "auth.permission",
    "pk": 21,
    "fields": {
      "name": "Can delete event location",
      "content_type": 7,
      "codename": "delete_eventlocation"
    }
  },
  {
    "model": "auth.permission",
    "pk": 22,
    "fields": {
      "name": "Can add event sponser",
      "content_type": 8,
      "codename": "add_eventsponser"
    }
  },
  {
    "model": "auth.permission",
    "pk": 23,
    "fields": {
      "name": "Can change event sponser",
      "content_type": 8,
      "codename": "change_eventsponser"
    }
  },
  {
    "model": "auth.permission",
    "pk": 24,
    "fields": {
      "name": "Can delete event sponser",
      "content_type": 8,
      "codename": "delete_eventsponser"
    }
  },
  {
    "model": "auth.permission",
    "pk": 25,
    "fields": {
      "name": "Can add organisation",
      "content_type": 9,
      "codename": "add_organisation"
    }
  },
  {
    "model": "auth.permission",
    "pk": 26,
    "fields": {
      "name": "Can change organisation",
      "content_type": 9,
      "codename": "change_organisation"
    }
  },
  {
    "model": "auth.permission",
    "pk": 27,
    "fields": {
      "name": "Can delete organisation",
      "content_type": 9,
      "codename": "delete_organisation"
    }
  },
  {
    "model": "auth.permission",
    "pk": 28,
    "fields": {
      "name": "Can add user",
      "content_type": 10,
      "codename": "add_user"
    }
  },
  {
    "model": "auth.permission",
    "pk": 29,
    "fields": {
      "name": "Can change user",
      "content_type": 10,
      "codename": "change_user"
    }
  },
  {
    "model": "auth.permission",
    "pk": 30,
    "fields": {
      "name": "Can delete user",
      "content_type": 10,
      "codename": "delete_user"
    }
  },
  {
    "model": "user.user",
    "pk": "4f3b9f10-6cd5-440d-bcb7-9f48c1a36942",
    "fields": {
      "password": "pbkdf2_sha256$100000$TU7YpD39UDt3$Z6i2pPdAtFBH4wm5NDHAL2BPgdhfwO7Ia67HRdpZ7wg=",
      "last_login": null,
      "is_superuser": true,
      "username": "admin",
      "email": "admin@test.com",
      "enable_notifications": true,
      "first_name": null,
      "last_name": null,
      "token": null,
      "is_active": true,
      "avatar": "",
      "groups": [],
      "user_permissions": []
    }
  },
  {
    "model": "organisation.organisation",
    "pk": 1,
    "fields": {
      "name": "Folio3",
      "description": "practical example",
      "is_active": false,
      "owner": "4f3b9f10-6cd5-440d-bcb7-9f48c1a36942",
      "logo": ""
    }
  },
  {
    "model": "organisation.organisation",
    "pk": 2,
    "fields": {
      "name": "HP",
      "description": "practical example",
      "is_active": false,
      "owner": "4f3b9f10-6cd5-440d-bcb7-9f48c1a36942",
      "logo": ""
    }
  }
]